Workbook

Sheet Timeline
A1: S.No | B1: Module | C1: Role | D1: Page | E1: Route | F1: Task to be done | G1: UI improvement | H1: Start date | I1: End date | J1: Window (working days) | K1: Status
A2: 1 | B2: Applicant | C2: Applicant | D2: Application list | E2: applicationform | F2: Show application number, type, status, and last updated date. Make the primary action depend on status: continue draft, view submitted, or open non-compliance. | G2: Align the page title with the new-application button on one row. Show status as a fixed-width badge, and keep row actions on a single line at the right edge of the table. | H2: 46307 | I2: 46307 | J2: =NETWORKDAYS(H2,I2) -> 1 | K2: Not started
A3: 2 | B3: Applicant | C3: Applicant | D3: New application shell | E3: applicationform/addapplicationform | F3: Keep the step list correct for Individual, Firm, Partnership, and Government. Restore the saved step after refresh and block a jump to a step that has no saved parent record. | G3: Lay the stepper out in one line with equal step widths and a clear active step. Pin Back and Next to a bottom bar so they stay in the same place on every step. | H3: 46307 | I3: 46307 | J3: =NETWORKDAYS(H3,I3) -> 1 | K3: Not started
A4: 3 | B4: Applicant | C4: Applicant | D4: Personal details | E4: applicationform/addapplicationform | F4: Validate name, date of birth, PAN, and contact fields. Keep the step label and success or error alert aligned with the application type. | G4: Place the personal-detail fields in a two-column grid with labels directly above each input and equal gaps. Show a field error under that input, and align Save to the right of the form. | H4: 46308 | I4: 46308 | J4: =NETWORKDAYS(H4,I4) -> 1 | K4: Not started
A5: 4 | B5: Applicant | C5: Applicant | D5: Address details | E5: applicationform/addapplicationform | F5: Require address, state, and city from the master lists. Reject an incomplete pin code and keep country, state, and city in a valid chain. | G5: Keep address, country, state, city, and pin code in one aligned grid. Make the dropdowns the same height as the text fields, and keep the error text from pushing the next field out of line. | H5: 46308 | I5: 46308 | J5: =NETWORKDAYS(H5,I5) -> 1 | K5: Not started
A6: 5 | B6: Applicant | C6: Applicant | D6: Financial details | E6: applicationform/addapplicationform | F6: Validate turnover and net-worth figures as numbers, require the supporting period, and show a clear message when a mandatory financial field is missing. | G6: Align amount fields and their labels on one vertical rhythm. Right-align numeric inputs, and keep the helper text directly under the field it describes. | H6: 46309 | I6: 46309 | J6: =NETWORKDAYS(H6,I6) -> 1 | K6: Not started
A7: 6 | B7: Applicant | C7: Applicant | D7: Additional details | E7: applicationform/addapplicationform | F7: Make every required question answerable, keep remarks mandatory where the answer needs an explanation, and preserve answers when the user moves back a step. | G7: Give each question the same spacing and a full-width answer control. Keep radio or checkbox options in a straight row, and place any remark box under the question that needs it. | H7: 46309 | I7: 46309 | J7: =NETWORKDAYS(H7,I7) -> 1 | K7: Not started
A8: 7 | B8: Applicant | C8: Applicant | D8: Firm details | E8: applicationform/addapplicationform | F8: Show this step only for firm and partnership types. Validate firm name, registration, and date of incorporation, and reject a future incorporation date. | G8: Group firm name, registration, and dates into one card with a visible heading. Keep date fields the same width, and align the action buttons with the other application steps. | H8: 46310 | I8: 46310 | J8: =NETWORKDAYS(H8,I8) -> 1 | K8: Not started
A9: 8 | B9: Applicant | C9: Applicant | D9: Income-tax documents | E9: applicationform/addapplicationform | F9: Restrict uploads to the allowed file types and size, require the assessment year, and let the user replace a file without leaving a broken document reference. | G9: Show each upload as a row with the document name, file name, and a replace action lined up in columns. Give the empty upload a clear drop area instead of a bare file input. | H9: 46310 | I9: 46310 | J9: =NETWORKDAYS(H9,I9) -> 1 | K9: Not started
A10: 9 | B10: Applicant | C10: Applicant | D10: Partner details | E10: applicationform/addapplicationform | F10: Require at least one partner for partnership applications. Validate each partner's identity fields and stop a blank partner row from being saved. | G10: Show partners as separate cards with the same internal field grid. Line up Add partner and Remove so they do not sit at different heights when a validation message appears. | H10: 46311 | I10: 46311 | J10: =NETWORKDAYS(H10,I10) -> 1 | K10: Not started
A11: 10 | B11: Applicant | C11: Applicant | D11: Authorized representative | E11: applicationform/addapplicationform | F11: Validate representative name, designation, and contact details. Keep the authorization document required before the step can be completed. | G11: Align the representative fields and the authorization upload on the same form grid. Keep the file name visible beside the upload button after a file is chosen. | H11: 46311 | I11: 46311 | J11: =NETWORKDAYS(H11,I11) -> 1 | K11: Not started
A12: 11 | B12: Applicant | C12: Applicant | D12: Organizational details | E12: applicationform/addapplicationform | F12: Show this step for government applications. Require organization name, ministry or department, and the authorized contact before save. | G12: Use one section heading and a single-column stack for organization, department, and contact. Match the input height and button placement used on the other government steps. | H12: 46314 | I12: 46314 | J12: =NETWORKDAYS(H12,I12) -> 1 | K12: Not started
A13: 12 | B13: Applicant | C13: Applicant | D13: Location of facility | E13: applicationform/addapplicationform | F13: Require at least one facility address. Validate city and state against masters and keep multiple locations editable without losing earlier rows. | G13: Show each facility as a card with address fields in a consistent grid. Keep Add location at the bottom left and the step actions at the bottom right. | H13: 46315 | I13: 46315 | J13: =NETWORKDAYS(H13,I13) -> 1 | K13: Not started
A14: 13 | B14: Applicant | C14: Applicant | D14: CPS and additional documents | E14: applicationform/addapplicationform | F14: Load the CPS document list from the master, mark mandatory documents, and block continue while a required file is missing or still uploading. | G14: List each CPS document in a table-like row: name, required marker, file, and action. Mark missing required files in the row itself so the gap is visible without scrolling to an alert. | H14: 46315 | I14: 46315 | J14: =NETWORKDAYS(H14,I14) -> 1 | K14: Not started
A15: 14 | B15: Applicant | C15: Applicant | D15: Individual checklist | E15: applicationform/addapplicationform | F15: Match checklist points to the individual application type. Require every point to be accepted before declaration. | G15: Show checklist points as a single column with the checkbox and the point text vertically centered. Keep the accept control from wrapping onto a second uneven line. | H15: 46316 | I15: 46316 | J15: 2 | K15: Not started
A16: 15 | B16: Applicant | C16: Applicant | D16: Firm checklist and declaration | E16: applicationform/addapplicationform | F16: Use the firm or partnership checklist, require the declaration text to be accepted, and keep the signatory name consistent with the saved representative. | G16: Separate the checklist and the declaration into two stacked sections with the same left margin. Make the declaration text readable, and place the acceptance checkbox on its own row above the buttons. | H16: 46316 | I16: 46316 | J16: 2 | K16: Not started
A17: 16 | B17: Applicant | C17: Applicant | D17: Government checklist and declaration | E17: applicationform/addapplicationform | F17: Use the government declaration wording and block submit until the organizational details and declaration are both complete. | G17: Use the same checklist spacing as the other declarations. Keep the government declaration block full width and the acceptance checkbox aligned with the first line of that text. | H17: 46316 | I17: 46316 | J17: 2 | K17: Not started
A18: 17 | B18: Applicant | C18: Applicant | D18: Submit preview | E18: applicationform/addapplicationform | F18: Show a read-only summary of every saved step. Final submit must use the final-submission message and return the user to the application list with status updated. | G18: Present the preview as labeled sections in the same order as the wizard. Use a definition layout for values, and put Edit and Submit on one button row at the bottom. | H18: 46316 | I18: 46316 | J18: 2 | K18: Not started
A19: 18 | B19: Applicant | C19: Applicant | D19: Application view | E19: applicationform | F19: Open a submitted application in read-only form for individual, firm, and government, with the same field labels used on the edit steps. | G19: Use the same section headings and two-column value layout for individual, firm, and government views. Keep long values from overflowing the card, and show document names as consistent links. | H19: 46317 | I19: 46317 | J19: 2 | K19: Not started
A20: 19 | B20: Applicant | C20: Applicant | D20: Non-compliance response | E20: applicationform/auditordetails/:id | F20: List auditor remarks, require the applicant's reply and evidence where a point is open, and keep closed points read-only. | G20: Show each remark as a card: finding, reply field, and evidence upload stacked with equal padding. Visually mute closed points so open points are the ones that stand out. | H20: 46317 | I20: 46317 | J20: =NETWORKDAYS(H20,I20) -> 1 | K20: Not started
A21: 20 | B21: Applicant | C21: Applicant | D21: Application audit controls | E21: applicationform/applicationauditordetails/:id | F21: Show each control with its result and the applicant action. Save a reply without clearing other controls on the same page. | G21: Put control text, result, and the reply on one aligned row. Keep the result control a fixed width so the reply field does not jump between rows. | H21: 46317 | I21: 46317 | J21: =NETWORKDAYS(H21,I21) -> 1 | K21: Not started
A22: 21 | B22: Applicant | C22: Applicant | D22: Select audit agency | E22: applicationform/selectauditagency/:id | F22: List only active audit agencies, confirm the selection, and prevent a second selection after one is already submitted. | G22: Show agencies as equal-height selectable cards or a clean table with one radio per row. Make the selected row obvious, and place Confirm on the right of the page footer. | H22: 46318 | I22: 46318 | J22: =NETWORKDAYS(H22,I22) -> 1 | K22: Not started
A23: 22 | B23: Applicant | C23: Applicant | D23: Payment proof | E23: applicationform/addapplicationform | F23: Require payment mode, reference, date, and proof file. Reject a future payment date and show the uploaded proof name after save. | G23: Align mode, reference, date, and the proof upload in one grid. Show the chosen file name under the upload control, and keep the date field the same width as the other inputs. | H23: 46318 | I23: 46318 | J23: =NETWORKDAYS(H23,I23) -> 1 | K23: Not started
A24: 23 | B24: Applicant | C24: Applicant | D24: Annexure A2 Home | E24: applicationform/selectauditagency/:id | F24: Open the annexure shell, show completion status per section, and block final submit until required sections are saved. | G24: On the applicant annexure, show the annexure title and a section list as equal rows with a completion mark on the left and the section name on one line. Keep the continue action in a footer. | H24: 46321 | I24: 46322 | J24: 2 | K24: Not started
A25: 24 | B25: Applicant | C25: Applicant | D25: CA Details | E25: applicationform/selectauditagency/:id | F25: Validate CA identity fields, licence number format, and required contact details before save. | G25: On the applicant annexure, lay identity and contact fields in a two-column grid with labels above the inputs. Keep licence number on its own row so it stays readable. | H25: 46321 | I25: 46322 | J25: 2 | K25: Not started
A26: 25 | B26: Applicant | C26: Applicant | D26: CA Service Details | E26: applicationform/selectauditagency/:id | F26: Keep selected services in sync with the licence, and stop empty or duplicate service rows. | G26: On the applicant annexure, show services as aligned rows with the service name and a remove action on the same baseline. Place Add service at the left of the section footer. | H26: 46321 | I26: 46322 | J26: 2 | K26: Not started
A27: 26 | B27: Applicant | C27: Applicant | D27: CA Self Assessment | E27: applicationform/selectauditagency/:id | F27: Require an answer for every assessment point and keep remarks mandatory when the answer is negative. | G27: On the applicant annexure, give every assessment point the same row height, with the answer control in a fixed column and the remark box full width under a negative answer. | H27: 46321 | I27: 46322 | J27: 2 | K27: Not started
A28: 27 | B28: Applicant | C28: Applicant | D28: Data Centre Details | E28: applicationform/selectauditagency/:id | F28: Validate site address, city, and capacity fields, and allow more than one centre without losing earlier rows. | G28: On the applicant annexure, show each centre as a card with the address grid inside. Keep Add centre outside the cards so it does not move when a card grows. | H28: 46321 | I28: 46322 | J28: 2 | K28: Not started
A29: 28 | B29: Applicant | C29: Applicant | D29: Trusted Persons List | E29: applicationform/selectauditagency/:id | F29: Validate person name, role, and identity fields, and prevent a blank row from being saved. | G29: On the applicant annexure, show people in a table or equal cards with name, role, and identity in fixed columns. Keep add and remove actions aligned. | H29: 46321 | I29: 46322 | J29: 2 | K29: Not started
A30: 29 | B30: Applicant | C30: Applicant | D30: ASP Details | E30: applicationform/selectauditagency/:id | F30: Validate ASP name and agreement dates, and reject an end date that falls before the start date. | G30: On the applicant annexure, align ASP name and the two agreement dates on one grid. Keep the date fields equal width and side by side. | H30: 46321 | I30: 46322 | J30: 2 | K30: Not started
A31: 30 | B31: Applicant | C31: Applicant | D31: Audit Details | E31: applicationform/selectauditagency/:id | F31: Capture audit period, agency, and outcome with required fields and a clear save confirmation. | G31: On the applicant annexure, group period, agency, and outcome in one card. Place the save confirmation area under the card, not as a floating message over the fields. | H31: 46321 | I31: 46322 | J31: 2 | K31: Not started
A32: 31 | B32: Applicant | C32: Applicant | D32: Internal Audit Details | E32: applicationform/selectauditagency/:id | F32: Require auditor name, period, and finding summary, and show a friendly error when save fails. | G32: On the applicant annexure, stack auditor, period, and finding summary with the summary full width. Match the field spacing used on Audit Details. | H32: 46321 | I32: 46322 | J32: 2 | K32: Not started
A33: 32 | B33: Applicant | C33: Applicant | D33: eKYC Audit Details | E33: applicationform/selectauditagency/:id | F33: Validate mode, volume, and exception counts, and reject non-numeric values in count fields. | G33: On the applicant annexure, right-align the count fields and keep mode, volume, and exceptions on one row on a wide screen. Keep labels from colliding with the inputs. | H33: 46321 | I33: 46322 | J33: 2 | K33: Not started
A34: 33 | B34: Applicant | C34: Applicant | D34: eKYC Verification Details | E34: applicationform/selectauditagency/:id | F34: Keep verification method and sample size required, and preserve entered values after a validation error. | G34: On the applicant annexure, align method and sample size on one row. Keep any error text under its own field so the row above does not jump. | H34: 46321 | I34: 46322 | J34: 2 | K34: Not started
A35: 34 | B35: Applicant | C35: Applicant | D35: Crypto Token Empanelment | E35: applicationform/selectauditagency/:id | F35: Validate token provider, approval status, and supporting reference before the section can be marked complete. | G35: On the applicant annexure, place provider, approval status, and reference in one card. Show approval status as a dropdown the same height as the text fields. | H35: 46321 | I35: 46322 | J35: 2 | K35: Not started
... A42: 41 | B42: Applicant | C42: Applicant | D42: RA Audit Details | E42: applicationform/selectauditagency/:id | F42: Validate registration authority name, audit period, and result, and show the saved summary on return to the section. | G42: On the applicant annexure, align authority name, period, and result on one card, and show the saved summary as a quiet line under the card. | H42: 46321 | I42: 46322 | J42: 2 | K42: Not started
A43: 42 | B43: Licensee | C43: Licensee | D43: View licence | E43: viewlicense | F43: Show licence number, validity, services, and the actions still open: renewal, cessation, eSign application, and annual audit. | G43: Show licence number, validity, and services in a summary strip at the top. Place renewal, cessation, eSign, and audit actions as equal buttons that wrap cleanly instead of overflowing. | H43: 46323 | I43: 46323 | J43: =NETWORKDAYS(H43,I43) -> 1 | K43: Not started
A44: 43 | B44: Licensee | C44: Licensee | D44: Renewal application list | E44: renewallicense | F44: Show renewal drafts and submitted renewals with status, and open the correct next step from each row. | G44: Match the new-application list: title and action on one row, status badge, and row actions aligned to the right. Keep renewal status labels from wrapping inside the badge. | H44: 46323 | I44: 46323 | J44: =NETWORKDAYS(H44,I44) -> 1 | K44: Not started
A45: 44 | B45: Licensee | C45: Licensee | D45: Renewal wizard | E45: renewallicense/renewallicenses | F45: Reuse the new-application step order for the licence type, and prefill fields from the current licence without letting stale draft data overwrite them silently. | G45: Reuse the same stepper, step spacing, and bottom button bar as the new-application wizard so the two flows look like one product. | H45: 46323 | I45: 46323 | J45: =NETWORKDAYS(H45,I45) -> 1 | K45: Not started
A46: 45 | B46: Licensee | C46: Licensee | D46: Renewal personal and address details | E46: renewallicense/renewallicenses | F46: Prefill personal and address data, validate edits the same way as a new application, and keep unchanged fields from being marked as missing. | G46: Use the same two-column grid as personal and address on a new application. Show prefilled values in the same input style, and keep edited and untouched fields visually identical. | H46: 46324 | I46: 46324 | J46: 2 | K46: Not started
A47: 46 | B47: Licensee | C47: Licensee | D47: Renewal financial and additional details | E47: renewallicense/renewallicenses | F47: Require the latest financial period and additional answers. Keep renewal-only fields visible and new-application-only fields hidden. | G47: Keep amount fields right-aligned and questions evenly spaced. Hide renewal-only blocks with the same card style as the rest of the step, not a different form. | H47: 46324 | I47: 46324 | J47: 2 | K47: Not started
A48: 47 | B48: Licensee | C48: Licensee | D48: Renewal firm, tax, partner, and representative | E48: renewallicense/renewallicenses | F48: Show firm, income-tax, partner, and representative steps only for the matching licence type, with the same validation as the new application. | G48: Split firm, tax, partner, and representative into stacked sections with matching headings and field grids. Keep upload rows aligned across those sections. | H48: 46324 | I48: 46324 | J48: 2 | K48: Not started
A49: 48 | B49: Licensee | C49: Licensee | D49: Renewal organization, location, and CPS | E49: renewallicense/renewallicenses | F49: Require current facility locations and the latest CPS documents. Allow replacement of an existing document and keep the previous file until the new one is saved. | G49: Use one heading per section and the same document-row layout as the new-application CPS step. Show the current file and the replace action on the same line. | H49: 46324 | I49: 46324 | J49: 2 | K49: Not started
A50: 49 | B50: Licensee | C50: Licensee | D50: Renewal declaration and preview | E50: renewallicense/renewallicenses | F50: Use the declaration that matches the licence type, show a full preview, and submit with a renewal-specific success message. | G50: Lay the declaration and the preview out as separate full-width sections. Keep the preview values in a two-column read-only grid and the submit button on the bottom right. | H50: 46324 | I50: 46324 | J50: 2 | K50: Not started
A51: 50 | B51: Licensee | C51: Licensee | D51: Renewal audit-agency selection | E51: agencyselection/selectauditagency/:id | F51: Let the licensee pick an audit agency for renewal only while the application is in the selection stage. | G51: Use the same agency card or table layout as the new-application selection screen. Show the renewal context in the page title so the screen is identifiable at a glance. | H51: 46325 | I51: 46325 | J51: =NETWORKDAYS(H51,I51) -> 1 | K51: Not started
A52: 51 | B52: Licensee | C52: Licensee | D52: Renewal non-compliance reply | E52: renewallicense/auditordetails/:id | F52: Show renewal audit remarks and require a reply and evidence for each open point. | G52: Repeat the open-point card layout from the new-application non-compliance screen. Keep evidence file names on one line and closed points visually quieter. | H52: 46325 | I52: 46325 | J52: =NETWORKDAYS(H52,I52) -> 1 | K52: Not started
A53: 52 | B53: Licensee | C53: Licensee | D53: Renewal audit controls | E53: renewallicense/applicationauditordetails/:id | F53: Save control-wise replies for the renewal audit without mixing them with the original licence audit. | G53: Align control, result, and reply in columns with a fixed result width. Match the spacing used on the original audit-control screen. | H53: 46325 | I53: 46325 | J53: =NETWORKDAYS(H53,I53) -> 1 | K53: Not started
A54: 53 | B54: Licensee | C54: Licensee | D54: Annexure A2 Home | E54: renewallicense/selectauditagency/:id | F54: Open the annexure shell, show completion status per section, and block final submit until required sections are saved. | G54: On the licensee annexure, show the annexure title and a section list as equal rows with a completion mark on the left and the section name on one line. Keep the continue action in a footer. | H54: 46328 | I54: 46328 | J54: =NETWORKDAYS(H54,I54) -> 1 | K54: Not started
A55: 54 | B55: Licensee | C55: Licensee | D55: CA Details | E55: renewallicense/selectauditagency/:id | F55: Validate CA identity fields, licence number format, and required contact details before save. | G55: On the licensee annexure, lay identity and contact fields in a two-column grid with labels above the inputs. Keep licence number on its own row so it stays readable. | H55: 46328 | I55: 46328 | J55: =NETWORKDAYS(H55,I55) -> 1 | K55: Not started
A56: 55 | B56: Licensee | C56: Licensee | D56: CA Service Details | E56: renewallicense/selectauditagency/:id | F56: Keep selected services in sync with the licence, and stop empty or duplicate service rows. | G56: On the licensee annexure, show services as aligned rows with the service name and a remove action on the same baseline. Place Add service at the left of the section footer. | H56: 46328 | I56: 46328 | J56: =NETWORKDAYS(H56,I56) -> 1 | K56: Not started
A57: 56 | B57: Licensee | C57: Licensee | D57: CA Self Assessment | E57: renewallicense/selectauditagency/:id | F57: Require an answer for every assessment point and keep remarks mandatory when the answer is negative. | G57: On the licensee annexure, give every assessment point the same row height, with the answer control in a fixed column and the remark box full width under a negative answer. | H57: 46328 | I57: 46328 | J57: =NETWORKDAYS(H57,I57) -> 1 | K57: Not started
A58: 57 | B58: Licensee | C58: Licensee | D58: Data Centre Details | E58: renewallicense/selectauditagency/:id | F58: Validate site address, city, and capacity fields, and allow more than one centre without losing earlier rows. | G58: On the licensee annexure, show each centre as a card with the address grid inside. Keep Add centre outside the cards so it does not move when a card grows. | H58: 46328 | I58: 46328 | J58: =NETWORKDAYS(H58,I58) -> 1 | K58: Not started
A59: 58 | B59: Licensee | C59: Licensee | D59: Trusted Persons List | E59: renewallicense/selectauditagency/:id | F59: Validate person name, role, and identity fields, and prevent a blank row from being saved. | G59: On the licensee annexure, show people in a table or equal cards with name, role, and identity in fixed columns. Keep add and remove actions aligned. | H59: 46328 | I59: 46328 | J59: =NETWORKDAYS(H59,I59) -> 1 | K59: Not started
A60: 59 | B60: Licensee | C60: Licensee | D60: ASP Details | E60: renewallicense/selectauditagency/:id | F60: Validate ASP name and agreement dates, and reject an end date that falls before the start date. | G60: On the licensee annexure, align ASP name and the two agreement dates on one grid. Keep the date fields equal width and side by side. | H60: 46328 | I60: 46328 | J60: =NETWORKDAYS(H60,I60) -> 1 | K60: Not started
A61: 60 | B61: Licensee | C61: Licensee | D61: Audit Details | E61: renewallicense/selectauditagency/:id | F61: Capture audit period, agency, and outcome with required fields and a clear save confirmation. | G61: On the licensee annexure, group period, agency, and outcome in one card. Place the save confirmation area under the card, not as a floating message over the fields. | H61: 46328 | I61: 46328 | J61: =NETWORKDAYS(H61,I61) -> 1 | K61: Not started
A62: 61 | B62: Licensee | C62: Licensee | D62: Internal Audit Details | E62: renewallicense/selectauditagency/:id | F62: Require auditor name, period, and finding summary, and show a friendly error when save fails. | G62: On the licensee annexure, stack auditor, period, and finding summary with the summary full width. Match the field spacing used on Audit Details. | H62: 46328 | I62: 46328 | J62: =NETWORKDAYS(H62,I62) -> 1 | K62: Not started
... A96: 95 | B96: Office of CCA | C96: CCA Officer | D96: eSign application detail | E96: espreviewapp/viewdetails/:id | F96: Show both eSign steps as read-only, and capture the office recommendation without editing the licensee's answers. | G96: Show both eSign steps as read-only sections under a status banner. Place the recommendation remark and buttons in a card at the bottom, separate from the licensee's answers. | H96: 46336 | I96: 46336 | J96: =NETWORKDAYS(H96,I96) -> 1 | K96: Not started
A97: 96 | B97: Review committee | C97: Review committee | D97: New application queue | E97: newapplication | F97: List new applications ready for committee review, with applicant type and current stage. | G97: Use a queue table with applicant, type, and stage in fixed columns. Keep the stage badge one width so the view action stays in a straight column. | H97: 46337 | I97: 46337 | J97: 2 | K97: Not started
A98: 97 | B98: Review committee | C98: Review committee | D98: Individual application review | E98: newapplication/reviewapplication/:id | F98: Show the individual application read-only, including documents, and record the committee remark against the application. | G98: Lay the individual file out in the same section order as the applicant form, read-only, in a two-column value grid. Pin the committee remark and action to the bottom card. | H98: 46337 | I98: 46337 | J98: 2 | K98: Not started
A99: 98 | B99: Review committee | C99: Review committee | D99: Firm application review | E99: newapplication/reviewapplications/:id | F99: Show firm or partnership details, partners, and documents with the same labels as the applicant form. | G99: Show firm, partner, and document blocks as separate headed sections. Keep partner rows in a compact table so the page does not become a long uneven form. | H99: 46337 | I99: 46337 | J99: 2 | K99: Not started
A100: 99 | B100: Review committee | C100: Review committee | D100: Government application review | E100: newapplication/reviewapplicationes/:id | F100: Show government organization details and documents, and keep fields that do not apply to government hidden. | G100: Show only the government sections, with organization and documents in headed cards. Align the remark box with the other review screens. | H100: 46337 | I100: 46337 | J100: 2 | K100: Not started
A101: 100 | B101: Review committee | C101: Review committee | D101: Pre-licence non-compliance | E101: ncreport | F101: List audits returned with non-compliance for committee review. | G101: List cases with applicant, stage, and a status badge. Keep the open action in a fixed right-hand column. | H101: 46337 | I101: 46337 | J101: 2 | K101: Not started
A102: 101 | B102: Review committee | C102: Review committee | D102: Non-compliance controls | E102: ncreport/ncreportbyid/:id | F102: Show each control, the auditor finding, and the applicant reply. Keep the committee view read-only except for the committee remark. | G102: Show finding, applicant reply, and evidence in a three-part card. Place the committee remark full width under the card, not beside a narrow column. | H102: 46337 | I102: 46337 | J102: 2 | K102: Not started
A103: 102 | B103: Review committee | C103: Review committee | D103: Renewal review queue | E103: renewapplication | F103: List renewal applications waiting for the committee, separate from new applications. | G103: Match the new-application queue layout and badge placement so the two lists look the same. | H103: 46338 | I103: 46338 | J103: =NETWORKDAYS(H103,I103) -> 1 | K103: Not started
A104: 103 | B104: Review committee | C104: Review committee | D104: Renewal individual review | E104: renewapplication/reviewapplication/:id | F104: Show the renewal individual file read-only and keep it distinct from the original licence application. | G104: Use the same read-only section grid as the individual review, with a renewal label in the page title. | H104: 46338 | I104: 46338 | J104: =NETWORKDAYS(H104,I104) -> 1 | K104: Not started
A105: 104 | B105: Review committee | C105: Review committee | D105: Renewal firm review | E105: renewapplication/reviewapplications/:id | F105: Show renewed firm, partner, and document data as submitted in the renewal, not the first licence file. | G105: Use the same firm, partner, and document sections as the firm review. Keep tables from stretching wider than the page. | H105: 46338 | I105: 46338 | J105: =NETWORKDAYS(H105,I105) -> 1 | K105: Not started
A106: 105 | B106: Review committee | C106: Review committee | D106: Renewal government review | E106: renewapplication/reviewapplicationes/:id | F106: Show the renewed government file read-only with organization and CPS documents. | G106: Use the same government read-only cards and bottom remark box as the new-application government review. | H106: 46338 | I106: 46338 | J106: =NETWORKDAYS(H106,I106) -> 1 | K106: Not started
A107: 106 | B107: Review committee | C107: Review committee | D107: Annual non-compliance queue | E107: reviewannualncreport | F107: List annual-audit non-compliance files waiting for the committee. | G107: Show licence, agency, and closure state in a table with a status badge and one review action. | H107: 46338 | I107: 46338 | J107: =NETWORKDAYS(H107,I107) -> 1 | K107: Not started
A108: 107 | B108: Review committee | C108: Review committee | D108: Annual non-compliance review | E108: reviewannualncreport/reviewannualncreports/:id | F108: Show the annual-audit finding, licensee reply, and closure status for each control. | G108: Stack finding, licensee reply, and closure state in equal cards. Show closure as a badge at the top of each card. | H108: 46338 | I108: 46338 | J108: =NETWORKDAYS(H108,I108) -> 1 | K108: Not started
A109: 108 | B109: CCA | C109: CCA | D109: Recommended new applications | E109: recommendednewapp | F109: List new applications recommended to CCA, with applicant, type, and recommendation date. | G109: Show applicant, type, and recommendation date in fixed columns with a type badge. Keep the open action aligned on the right. | H109: 46339 | I109: 46339 | J109: 2 | K109: Not started
A110: 109 | B110: CCA | C110: CCA | D110: Recommended renewal applications | E110: recommendedrenewalapp | F110: List renewal recommendations separately, with the current licence number visible. | G110: Match the recommended-new list, and give the current licence number its own column so it does not wrap under the applicant name. | H110: 46339 | I110: 46339 | J110: 2 | K110: Not started
A111: 110 | B111: CCA | C111: CCA | D111: Issue new licence | E111: issuenewlicense | F111: Issue a licence only from an approved recommendation. Capture licence number and validity, then show the issued licence in the licensee view. | G111: Group licence number and validity in a short form card under a read-only application summary. Place Issue on the right and keep the summary from colliding with the form. | H111: 46339 | I111: 46339 | J111: 2 | K111: Not started
A112: 111 | B112: CCA | C112: CCA | D112: Approve application | E112: approvedreviewapplication | F112: Open applications approved for issue and link each row to the individual, firm, or government view. | G112: Use the same recommendation-list layout, with applicant type as a badge and one view action per row. | H112: 46339 | I112: 46339 | J112: 2 | K112: Not started
A113: 112 | B113: CCA | C113: CCA | D113: Approved individual view | E113: approvedreviewapplication/indivreviewapplication/:id | F113: Show the approved individual file read-only, including payment and documents used for the decision. | G113: Show a decision banner, then the individual file in a two-column read-only grid. Keep document links on one line. | H113: 46339 | I113: 46339 | J113: 2 | K113: Not started
A114: 113 | B114: CCA | C114: CCA | D114: Approved firm view | E114: approvedreviewapplication/firmreviewapplication/:id | F114: Show the approved firm file read-only with partners and declarations. | G114: Use a decision banner and headed sections for firm, partners, and declaration. Keep partner details in a table. | H114: 46339 | I114: 46339 | J114: 2 | K114: Not started
A115: 114 | B115: CCA | C115: CCA | D115: Approved government view | E115: approvedreviewapplication/govreviewapplication/:id | F115: Show the approved government file read-only with organization and CPS documents. | G115: Use a decision banner and headed cards for organization and CPS documents. Align the document list as rows. | H115: 46339 | I115: 46339 | J115: 2 | K115: Not started
A116: 115 | B116: CCA | C116: CCA | D116: Rejected new-application review | E116: rejectedreviewapplication | F116: List applications recommended for rejection and open the matching applicant-type view. | G116: Match the recommended-list layout and add a clear path to the individual, firm, or government view. | H116: 46342 | I116: 46342 | J116: 2 | K116: Not started
A117: 116 | B117: CCA | C117: CCA | D117: Rejected individual view | E117: rejectedreviewapplication/indivreviewapplication/:id | F117: Show the individual file and require a rejection remark before the decision is saved. | G117: Show the individual file read-only and a separate decision card for the rejection remark. Make the remark full width and the confirm button right-aligned. | H117: 46342 | I117: 46342 | J117: =NETWORKDAYS(H117,I117) -> 1 | K117: Not started
A118: 117 | B118: CCA | C118: CCA | D118: Rejected firm view | E118: rejectedreviewapplication/firmreviewapplication/:id | F118: Show the firm file and save the rejection remark against that application only. | G118: Use the same split: firm file above, decision card below. Keep the remark from sitting in a narrow side column. | H118: 46342 | I118: 46342 | J118: =NETWORKDAYS(H118,I118) -> 1 | K118: Not started
A119: 118 | B119: CCA | C119: CCA | D119: Rejected government view | E119: rejectedreviewapplication/govreviewapplication/:id | F119: Show the government file and save the rejection remark with the decision. | G119: Use the same file-plus-decision-card layout as the other rejection views. | H119: 46342 | I119: 46342 | J119: =NETWORKDAYS(H119,I119) -> 1 | K119: Not started
A120: 119 | B120: CCA | C120: CCA | D120: Renewal approval review | E120: renewapprovedapplication | F120: List renewals recommended for approval and open the renewal file, not the original application. | G120: Match the approval queue layout and show the licence number in its own column. | H120: 46342 | I120: 46342 | J120: =NETWORKDAYS(H120,I120) -> 1 | K120: Not started
A121: 120 | B121: CCA | C121: CCA | D121: Renewal rejection review | E121: renewrejectedapplication | F121: List renewals recommended for rejection and require a remark on the individual, firm, or government renewal view. | G121: Match the rejection queue layout, with type badges and a single open action. | H121: 46342 | I121: 46342 | J121: =NETWORKDAYS(H121,I121) -> 1 | K121: Not started
A122: 121 | B122: CCA | C122: CCA | D122: Audit of licence | E122: auditorlicense | F122: List licence audits waiting for CCA, with agency, period, and stage. | G122: Show agency, period, and stage in fixed columns. Use a stage badge and keep the period on one line. | H122: 46343 | I122: 46343 | J122: =NETWORKDAYS(H122,I122) -> 1 | K122: Not started
A123: 122 | B123: CCA | C123: CCA | D123: Audit detail | E123: auditorlicense/auditordetails/:id | F123: Show auditor controls and findings read-only, with a path to send the case back or reject. | G123: Show controls and findings in a readable table, with result as a badge. Place the send-back and reject actions in a footer, not inside the table. | H123: 46343 | I123: 46343 | J123: =NETWORKDAYS(H123,I123) -> 1 | K123: Not started
A124: 123 | B124: CCA | C124: CCA | D124: Send audit to rejection | E124: auditorlicense/sendToRejection/:id | F124: Require a rejection reason, confirm the action, and remove the case from the pending audit list after save. | G124: Keep the reason field full width in a single card, with Cancel and Confirm as a right-aligned pair. Show the case identity in a summary line above the field. | H124: 46343 | I124: 46343 | J124: =NETWORKDAYS(H124,I124) -> 1 | K124: Not started
A125: 124 | B125: CCA | C125: CCA | D125: Annual audit list | E125: uploadannualundertakings | F125: List annual audits submitted to CCA and show whether each one is on time against the schedule. | G125: Add an on-time or late badge in a fixed column beside the due date. Keep the rest of the row on the same list style as the other CCA queues. | H125: 46343 | I125: 46343 | J125: =NETWORKDAYS(H125,I125) -> 1 | K125: Not started
A126: 125 | B126: CCA | C126: CCA | D126: Annual audit report | E126: uploadannualundertakings/annualauditreports/:id | F126: Open the annual audit report, findings, and annexure summary in read-only form. | G126: Show the report header, findings, and annexure summary as three stacked sections. Keep the report file link in the header, not buried in the findings. | H126: 46343 | I126: 46343 | J126: =NETWORKDAYS(H126,I126) -> 1 | K126: Not started
A127: 126 | B127: CCA | C127: CCA | D127: Cessation for CCA | E127: cessationapplicationforcca | F127: List cessation files forwarded to CCA. | G127: Use the CCA queue pattern: licence, status badge, and one open action. | H127: 46344 | I127: 46344 | J127: =NETWORKDAYS(H127,I127) -> 1 | K127: Not started
A128: 127 | B128: CCA | C128: CCA | D128: Cessation undertaking view | E128: cessationapplicationforcca/editlicensecessationchecklist/:id | F128: Show the cessation checklist and notice, and record CCA's decision. | G128: Show the checklist and notice in two panes, with the decision card underneath spanning both. | H128: 46344 | I128: 46344 | J128: =NETWORKDAYS(H128,I128) -> 1 | K128: Not started
... A142: 141 | B142: CCA | C142: CCA | D142: Approved eSign detail | E142: espappcapproved/viewcprevappdetails/:id | F142: Open an approved eSign file read-only. | G142: Use an approved banner and the same read-only section grid. | H142: 46345 | I142: 46345 | J142: =NETWORKDAYS(H142,I142) -> 1 | K142: Not started
A143: 142 | B143: Audit agency | C143: Audit agency | D143: Undertaking queue | E143: uploadundertaking | F143: List applications assigned to the agency for audit, with applicant, type, and stage. | G143: Show applicant, type, and stage as a queue table with badges and a right-aligned open action. | H143: 46346 | I143: 46346 | J143: 2 | K143: Not started
A144: 143 | B144: Audit agency | C144: Audit agency | D144: Auditor details | E144: uploadundertaking/auditordetails/:id | F144: Capture auditor name, visit dates, and report reference. Reject a visit end date before the start date. | G144: Align auditor name, visit dates, and report reference on one form grid. Keep the two date fields equal width and the report upload on its own full-width row. | H144: 46346 | I144: 46346 | J144: 2 | K144: Not started
A145: 144 | B145: Audit agency | C145: Audit agency | D145: Auditor controls | E145: uploadundertaking/auditorcontrols/:id | F145: Score each control, require a remark when the result is non-compliant, and save one control without wiping the others. | G145: Make each control a row: text, result, and remark. Give non-compliant rows a visible left border so they stand out from compliant ones. | H145: 46346 | I145: 46346 | J145: 2 | K145: Not started
A146: 145 | B146: Audit agency | C146: Audit agency | D146: Non-compliance closure | E146: uploadundertaking/ncclosurereport/:id | F146: Show the applicant's corrective action and let the auditor close or reopen each point with a remark. | G146: Show the applicant action and the auditor close or reopen controls in two columns of one card. Keep a remark field full width under them. | H146: 46346 | I146: 46346 | J146: 2 | K146: Not started
A147: 146 | B147: Audit agency | C147: Audit agency | D147: View annexure | E147: uploadundertaking/annexurea/:id | F147: Open the applicant's annexure read-only from the audit file, section by section. | G147: Show annexure sections as a vertical list of cards with a section title and a completion mark. Keep the open-section action aligned on the right of every card. | H147: 46346 | I147: 46346 | J147: 2 | K147: Not started
A148: 147 | B148: Audit agency | C148: Audit agency | D148: Pre-licence non-compliance list | E148: reviewauditreport | F148: List audits sent back after the applicant's reply so the agency can review them again. | G148: Use the agency queue layout with applicant, stage, and a status badge. | H148: 46346 | I148: 46346 | J148: 2 | K148: Not started
A149: 148 | B149: Audit agency | C149: Audit agency | D149: Pre-licence non-compliance review | E149: reviewauditreport/reviewreport/:id | F149: Compare the original finding with the applicant reply and record the revised result. | G149: Place the original finding and the applicant reply side by side, and the revised result full width underneath. | H149: 46346 | I149: 46346 | J149: 2 | K149: Not started
A150: 149 | B150: Audit agency | C150: Audit agency | D150: Annexure A2 Home | E150: uploadundertaking/annexurea/:id | F150: Open the annexure shell, show completion status per section, and block final submit until required sections are saved. | G150: On the audit agency annexure, show the annexure title and a section list as equal rows with a completion mark on the left and the section name on one line. Keep the continue action in a footer. | H150: 46349 | I150: 46350 | J150: 2 | K150: Not started
A151: 150 | B151: Audit agency | C151: Audit agency | D151: CA Details | E151: uploadundertaking/annexurea/:id | F151: Validate CA identity fields, licence number format, and required contact details before save. | G151: On the audit agency annexure, lay identity and contact fields in a two-column grid with labels above the inputs. Keep licence number on its own row so it stays readable. | H151: 46349 | I151: 46350 | J151: 2 | K151: Not started
A152: 151 | B152: Audit agency | C152: Audit agency | D152: CA Service Details | E152: uploadundertaking/annexurea/:id | F152: Keep selected services in sync with the licence, and stop empty or duplicate service rows. | G152: On the audit agency annexure, show services as aligned rows with the service name and a remove action on the same baseline. Place Add service at the left of the section footer. | H152: 46349 | I152: 46350 | J152: 2 | K152: Not started
...

Sheet Module summary
A1: Module | B1: Role | C1: Pages | D1: Start | E1: End | F1: Not started | G1: In progress | H1: Blocked | I1: Done
A2: Applicant | B2: Applicant | C2: =COUNTIFS(Timeline!B:B,A2,Timeline!C:C,B2) -> 41 | F2: =COUNTIFS(Timeline!B:B,A2,Timeline!C:C,B2,Timeline!K:K,"Not started") -> 41 | G2: =COUNTIFS(Timeline!B:B,A2,Timeline!C:C,B2,Timeline!K:K,"In progress") -> 0 | H2: =COUNTIFS(Timeline!B:B,A2,Timeline!C:C,B2,Timeline!K:K,"Blocked") -> 0 | I2: =COUNTIFS(Timeline!B:B,A2,Timeline!C:C,B2,Timeline!K:K,"Done") -> 0
A3: Licensee | B3: Licensee | C3: =COUNTIFS(Timeline!B:B,A3,Timeline!C:C,B3) -> 41 | F3: =COUNTIFS(Timeline!B:B,A3,Timeline!C:C,B3,Timeline!K:K,"Not started") -> 41 | G3: =COUNTIFS(Timeline!B:B,A3,Timeline!C:C,B3,Timeline!K:K,"In progress") -> 0 | H3: =COUNTIFS(Timeline!B:B,A3,Timeline!C:C,B3,Timeline!K:K,"Blocked") -> 0 | I3: =COUNTIFS(Timeline!B:B,A3,Timeline!C:C,B3,Timeline!K:K,"Done") -> 0
A4: Office of CCA | B4: CCA Officer | C4: =COUNTIFS(Timeline!B:B,A4,Timeline!C:C,B4) -> 13 | F4: =COUNTIFS(Timeline!B:B,A4,Timeline!C:C,B4,Timeline!K:K,"Not started") -> 13 | G4: =COUNTIFS(Timeline!B:B,A4,Timeline!C:C,B4,Timeline!K:K,"In progress") -> 0 | H4: =COUNTIFS(Timeline!B:B,A4,Timeline!C:C,B4,Timeline!K:K,"Blocked") -> 0 | I4: =COUNTIFS(Timeline!B:B,A4,Timeline!C:C,B4,Timeline!K:K,"Done") -> 0
A5: Review committee | B5: Review committee | C5: =COUNTIFS(Timeline!B:B,A5,Timeline!C:C,B5) -> 12 | F5: =COUNTIFS(Timeline!B:B,A5,Timeline!C:C,B5,Timeline!K:K,"Not started") -> 12 | G5: =COUNTIFS(Timeline!B:B,A5,Timeline!C:C,B5,Timeline!K:K,"In progress") -> 0 | H5: =COUNTIFS(Timeline!B:B,A5,Timeline!C:C,B5,Timeline!K:K,"Blocked") -> 0 | I5: =COUNTIFS(Timeline!B:B,A5,Timeline!C:C,B5,Timeline!K:K,"Done") -> 0
A6: CCA | B6: CCA | C6: =COUNTIFS(Timeline!B:B,A6,Timeline!C:C,B6) -> 34 | F6: =COUNTIFS(Timeline!B:B,A6,Timeline!C:C,B6,Timeline!K:K,"Not started") -> 34 | G6: =COUNTIFS(Timeline!B:B,A6,Timeline!C:C,B6,Timeline!K:K,"In progress") -> 0 | H6: =COUNTIFS(Timeline!B:B,A6,Timeline!C:C,B6,Timeline!K:K,"Blocked") -> 0 | I6: =COUNTIFS(Timeline!B:B,A6,Timeline!C:C,B6,Timeline!K:K,"Done") -> 0
A7: Audit agency | B7: Audit agency | C7: =COUNTIFS(Timeline!B:B,A7,Timeline!C:C,B7) -> 34 | F7: =COUNTIFS(Timeline!B:B,A7,Timeline!C:C,B7,Timeline!K:K,"Not started") -> 34 | G7: =COUNTIFS(Timeline!B:B,A7,Timeline!C:C,B7,Timeline!K:K,"In progress") -> 0 | H7: =COUNTIFS(Timeline!B:B,A7,Timeline!C:C,B7,Timeline!K:K,"Blocked") -> 0 | I7: =COUNTIFS(Timeline!B:B,A7,Timeline!C:C,B7,Timeline!K:K,"Done") -> 0
A8: Dashboards | B8: CCA | C8: =COUNTIFS(Timeline!B:B,A8,Timeline!C:C,B8) -> 5 | F8: =COUNTIFS(Timeline!B:B,A8,Timeline!C:C,B8,Timeline!K:K,"Not started") -> 5 | G8: =COUNTIFS(Timeline!B:B,A8,Timeline!C:C,B8,Timeline!K:K,"In progress") -> 0 | H8: =COUNTIFS(Timeline!B:B,A8,Timeline!C:C,B8,Timeline!K:K,"Blocked") -> 0 | I8: =COUNTIFS(Timeline!B:B,A8,Timeline!C:C,B8,Timeline!K:K,"Done") -> 0
A9: Dashboards | B9: CCA Officer | C9: =COUNTIFS(Timeline!B:B,A9,Timeline!C:C,B9) -> 1 | F9: =COUNTIFS(Timeline!B:B,A9,Timeline!C:C,B9,Timeline!K:K,"Not started") -> 1 | G9: =COUNTIFS(Timeline!B:B,A9,Timeline!C:C,B9,Timeline!K:K,"In progress") -> 0 | H9: =COUNTIFS(Timeline!B:B,A9,Timeline!C:C,B9,Timeline!K:K,"Blocked") -> 0 | I9: =COUNTIFS(Timeline!B:B,A9,Timeline!C:C,B9,Timeline!K:K,"Done") -> 0
A10: Dashboards | B10: Admin | C10: =COUNTIFS(Timeline!B:B,A10,Timeline!C:C,B10) -> 1 | F10: =COUNTIFS(Timeline!B:B,A10,Timeline!C:C,B10,Timeline!K:K,"Not started") -> 1 | G10: =COUNTIFS(Timeline!B:B,A10,Timeline!C:C,B10,Timeline!K:K,"In progress") -> 0 | H10: =COUNTIFS(Timeline!B:B,A10,Timeline!C:C,B10,Timeline!K:K,"Blocked") -> 0 | I10: =COUNTIFS(Timeline!B:B,A10,Timeline!C:C,B10,Timeline!K:K,"Done") -> 0
A11: Operations data | B11: Licensee | C11: =COUNTIFS(Timeline!B:B,A11,Timeline!C:C,B11) -> 6 | F11: =COUNTIFS(Timeline!B:B,A11,Timeline!C:C,B11,Timeline!K:K,"Not started") -> 6 | G11: =COUNTIFS(Timeline!B:B,A11,Timeline!C:C,B11,Timeline!K:K,"In progress") -> 0 | H11: =COUNTIFS(Timeline!B:B,A11,Timeline!C:C,B11,Timeline!K:K,"Blocked") -> 0 | I11: =COUNTIFS(Timeline!B:B,A11,Timeline!C:C,B11,Timeline!K:K,"Done") -> 0
A12: Reports | B12: CCA Officer | C12: =COUNTIFS(Timeline!B:B,A12,Timeline!C:C,B12) -> 18 | F12: =COUNTIFS(Timeline!B:B,A12,Timeline!C:C,B12,Timeline!K:K,"Not started") -> 18 | G12: =COUNTIFS(Timeline!B:B,A12,Timeline!C:C,B12,Timeline!K:K,"In progress") -> 0 | H12: =COUNTIFS(Timeline!B:B,A12,Timeline!C:C,B12,Timeline!K:K,"Blocked") -> 0 | I12: =COUNTIFS(Timeline!B:B,A12,Timeline!C:C,B12,Timeline!K:K,"Done") -> 0
A13: Admin masters | B13: Admin | C13: =COUNTIFS(Timeline!B:B,A13,Timeline!C:C,B13) -> 89 | F13: =COUNTIFS(Timeline!B:B,A13,Timeline!C:C,B13,Timeline!K:K,"Not started") -> 89 | G13: =COUNTIFS(Timeline!B:B,A13,Timeline!C:C,B13,Timeline!K:K,"In progress") -> 0 | H13: =COUNTIFS(Timeline!B:B,A13,Timeline!C:C,B13,Timeline!K:K,"Blocked") -> 0 | I13: =COUNTIFS(Timeline!B:B,A13,Timeline!C:C,B13,Timeline!K:K,"Done") -> 0
A14: Total | C14: =SUM(C2:C13) -> 295 | F14: =SUM(F2:F13) -> 295 | G14: =SUM(G2:G13) -> 0 | H14: =SUM(H2:H13) -> 0 | I14: =SUM(I2:I13) -> 0
